ponytAIl/__init__.py
ponytAIl/main.py
ponytAIl/nodes_sample/concluder.md
ponytAIl/nodes_sample/medium_sample.md
ponytAIl/nodes_sample/node_creator.md
ponytAIl/nodes_sample/starter.md
ponytAIl/nodes_sample_definition_of_one/concluder.md
ponytAIl/nodes_sample_definition_of_one/example_generator.md
ponytAIl/nodes_sample_definition_of_one/math_concept_definition.md
ponytAIl/nodes_sample_definition_of_one/medium_sample.md
ponytAIl/nodes_sample_definition_of_one/node_creator.md
ponytAIl/nodes_sample_definition_of_one/starter.md
ponytAIl/nodes_sample_ponytail/concluder.md
ponytAIl/nodes_sample_ponytail/medium_sample.md
ponytAIl/nodes_sample_ponytail/name_combiner.md
ponytAIl/nodes_sample_ponytail/name_generator.md
ponytAIl/nodes_sample_ponytail/node_creator.md
ponytAIl/nodes_sample_ponytail/starter.md
ponytAIl/nodes_sample_villagers/anita_kumar.md
ponytAIl/nodes_sample_villagers/concluder.md
ponytAIl/nodes_sample_villagers/david_brown.md
ponytAIl/nodes_sample_villagers/gloria_martinez.md
ponytAIl/nodes_sample_villagers/john_smith.md
ponytAIl/nodes_sample_villagers/kevin_white.md
ponytAIl/nodes_sample_villagers/li_wang.md
ponytAIl/nodes_sample_villagers/maria_garcia.md
ponytAIl/nodes_sample_villagers/medium_sample.md
ponytAIl/nodes_sample_villagers/michael_clark.md
ponytAIl/nodes_sample_villagers/node_creator.md
ponytAIl/nodes_sample_villagers/sarah_johnson.md
ponytAIl/nodes_sample_villagers/starter.md
ponytAIl/nodes_sample_villagers/yuki_tanaka.md
ponytAIl/nodes_sample_villagers_2/Ahmed_El-Sayed.md
ponytAIl/nodes_sample_villagers_2/Aisha_Khan.md
ponytAIl/nodes_sample_villagers_2/Carlos_Mendez.md
ponytAIl/nodes_sample_villagers_2/Elena_Petrov.md
ponytAIl/nodes_sample_villagers_2/Emily_Johnson.md
ponytAIl/nodes_sample_villagers_2/Emma_Jones.md
ponytAIl/nodes_sample_villagers_2/Fatou_Sangare.md
ponytAIl/nodes_sample_villagers_2/Haruto_Yamamoto.md
ponytAIl/nodes_sample_villagers_2/John_Smith.md
ponytAIl/nodes_sample_villagers_2/Keisha_Anderson.md
ponytail_agents-0.1.8.dist-info/LICENSE
ponytail_agents-0.1.8.dist-info/METADATA
ponytail_agents-0.1.8.dist-info/WHEEL
ponytail_agents-0.1.8.dist-info/entry_points.txt
ponytail_agents-0.1.8.dist-info/top_level.txt
ponytail_agents-0.1.8.dist-info/RECORD
