Metadata-Version: 2.1
Name: ponytail-agents
Version: 0.1.8
Summary: ponytAIl: Polymorphic Orchestration of Networked Youthful, Adaptable Intelligence with Language.
Home-page: https://github.com/thepioneerjp/ponytAIl
Author: The Pioneer
Classifier: Development Status :: 3 - Alpha
Classifier: Intended Audience :: Developers
Classifier: Programming Language :: Python :: 3
License-File: LICENSE
Requires-Dist: openai
Requires-Dist: anthropic
Requires-Dist: google-generativeai
Requires-Dist: python-dotenv
Requires-Dist: pytest
Requires-Dist: flute-llm
